setup.py
tic_tac_toe/__init__.py
tic_tac_toe_api_bot.egg-info/PKG-INFO
tic_tac_toe_api_bot.egg-info/SOURCES.txt
tic_tac_toe_api_bot.egg-info/dependency_links.txt
tic_tac_toe_api_bot.egg-info/not-zip-safe
tic_tac_toe_api_bot.egg-info/top_level.txt