Metadata-Version: 2.1
Name: tic-tac-toe-api-bot
Version: 0.2.7
Summary: simple bot for tic tac toe
Home-page: https://github.com/ruslan-ilesik/tic-tac-toe-bot-pip-package
Author: lesikr
License: MIT
Keywords: tic_tac_toe bot api game_api
Platform: UNKNOWN
Classifier: Development Status :: 3 - Alpha
Classifier: License :: OSI Approved :: MIT License
Classifier: Programming Language :: Python :: 3.8
